Workbook

Sheet Qualifier_Analysis_2025-01-01
A1: Qualifier | B1: Allowed as Qualifier | C1: Count as Qualifier | D1: Label | E1: Category | F1: Subcategory | G1: Frequency | H1: Abundance | I1: 1D Diversity | J1: 1D Proportional Diversity | K1: Importantce F * 1DPD | M1: Comment
B2: =SUM(B3:B15000) -> 1850 | C2: =SUM(C3:C15000) -> 1357
A3: P1545 | B3: =_xlfn.XLOOKUP(A3,'Allowed as Qualifiers'!$A$1:$A$1896,'Allowed as Qualifiers'!$B$1:$B$1896,0) -> 1 | C3: =IF(B3=1,1,0)*IF(G3>0,1,0) -> 1 | D3: series ordinal | E3: A | F3: Sequence | G3: 198557380 | H3: =_xlfn.XLOOKUP(A3,'Diversity Analysis'!$A$2:$A$2366,'Diversity Analysis'!$F$2:$F$2366,"") -> 592 | I3: 2.2972161 | J3: 60.986634 | K3: =G3/1000000*J3 -> 12109.346
A4: P1810 | B4: =_xlfn.XLOOKUP(A4,'Allowed as Qualifiers'!$A$1:$A$1896,'Allowed as Qualifiers'!$B$1:$B$1896,0) -> 1 | C4: =IF(B4=1,1,0)*IF(G4>0,1,0) -> 1 | D4: subject named as | E4: A | F4: Provenance | G4: 6480845 | H4: =_xlfn.XLOOKUP(A4,'Diversity Analysis'!$A$2:$A$2366,'Diversity Analysis'!$F$2:$F$2366,"") -> 4409 | I4: 74.628448 | J4: 716.95669 | K4: =G4/1000000*J4 -> 4646.4852 | M4: mostly for Ext. Obj. Desc. execpt described by source
A5: P585 | B5: =_xlfn.XLOOKUP(A5,'Allowed as Qualifiers'!$A$1:$A$1896,'Allowed as Qualifiers'!$B$1:$B$1896,0) -> 1 | C5: =IF(B5=1,1,0)*IF(G5>0,1,0) -> 1 | D5: point in time | E5: Ctxt | F5: Time | G5: 14667663 | H5: =_xlfn.XLOOKUP(A5,'Diversity Analysis'!$A$2:$A$2366,'Diversity Analysis'!$F$2:$F$2366,"") -> 1510 | I5: 22.605733 | J5: 292.34028 | K5: =G5/1000000*J5 -> 4287.9487 | R5: Time | S5: =COUNTIF($F$3:$F$53,R5) -> 4 | T5: =COUNTIF($F$3:$F$306,R5) -> 8
A6: P580 | B6: =_xlfn.XLOOKUP(A6,'Allowed as Qualifiers'!$A$1:$A$1896,'Allowed as Qualifiers'!$B$1:$B$1896,0) -> 1 | C6: =IF(B6=1,1,0)*IF(G6>0,1,0) -> 1 | D6: start time | E6: Ctxt | F6: Time | G6: 11563055 | H6: =_xlfn.XLOOKUP(A6,'Diversity Analysis'!$A$2:$A$2366,'Diversity Analysis'!$F$2:$F$2366,"") -> 1727 | I6: 24.126413 | J6: 300.22414 | K6: =G6/1000000*J6 -> 3471.5082 | R6: Space | S6: =COUNTIF($F$3:$F$53,R6) -> 1 | T6: =COUNTIF($F$3:$F$306,R6) -> 4
A7: P1932 | B7: =_xlfn.XLOOKUP(A7,'Allowed as Qualifiers'!$A$1:$A$1896,'Allowed as Qualifiers'!$B$1:$B$1896,0) -> 1 | C7: =IF(B7=1,1,0)*IF(G7>0,1,0) -> 1 | D7: object named as | E7: A | F7: Provenance | G7: 22167461 | H7: =_xlfn.XLOOKUP(A7,'Diversity Analysis'!$A$2:$A$2366,'Diversity Analysis'!$F$2:$F$2366,"") -> 1096 | I7: 1.6783922 | J7: 75.626808 | K7: =G7/1000000*J7 -> 1676.4543 | R7: Subject Modifier | S7: =COUNTIF($F$3:$F$53,R7) -> 1 | T7: =COUNTIF($F$3:$F$306,R7) -> 4
A8: P582 | B8: =_xlfn.XLOOKUP(A8,'Allowed as Qualifiers'!$A$1:$A$1896,'Allowed as Qualifiers'!$B$1:$B$1896,0) -> 1 | C8: =IF(B8=1,1,0)*IF(G8>0,1,0) -> 1 | D8: end time | E8: Ctxt | F8: Time | G8: 5440957 | H8: =_xlfn.XLOOKUP(A8,'Diversity Analysis'!$A$2:$A$2366,'Diversity Analysis'!$F$2:$F$2366,"") -> 1483 | I8: 16.736172 | J8: 216.79831 | K8: =G8/1000000*J8 -> 1179.5903 | R8: Epistemic | S8: =COUNTIF($F$3:$F$53,R8) -> 1 | T8: =COUNTIF($F$3:$F$306,R8) -> 3
A9: P459 | B9: =_xlfn.XLOOKUP(A9,'Allowed as Qualifiers'!$A$1:$A$1896,'Allowed as Qualifiers'!$B$1:$B$1896,0) -> 1 | C9: =IF(B9=1,1,0)*IF(G9>0,1,0) -> 1 | D9: determination method or standard | E9: A | F9: Provenance | G9: 9624947 | H9: =_xlfn.XLOOKUP(A9,'Diversity Analysis'!$A$2:$A$2366,'Diversity Analysis'!$F$2:$F$2366,"") -> 358 | I9: 9.3376637 | J9: 75.433105 | K9: =G9/1000000*J9 -> 726.03963 | R9: Uncertainty Quantification | S9: =COUNTIF($F$3:$F$53,R9) -> 2 | T9: =COUNTIF($F$3:$F$306,R9) -> 5
A10: P407 | B10: =_xlfn.XLOOKUP(A10,'Allowed as Qualifiers'!$A$1:$A$1896,'Allowed as Qualifiers'!$B$1:$B$1896,0) -> 1 | C10: =IF(B10=1,1,0)*IF(G10>0,1,0) -> 1 | D10: language of work or name | E10: A | F10: External Object Description | G10: 2207095 | H10: =_xlfn.XLOOKUP(A10,'Diversity Analysis'!$A$2:$A$2366,'Diversity Analysis'!$F$2:$F$2366,"") -> 1485 | I10: 9.4893184 | J10: 155.43341 | K10: =G10/1000000*J10 -> 343.0563 | M10: when the value is a reference (URL, ID, …) description of the referent | R10: Structured Value | S10: =COUNTIF($F$3:$F$53,R10) -> 7 | T10: =COUNTIF($F$3:$F$306,R10) -> 17
A11: P518 | B11: =_xlfn.XLOOKUP(A11,'Allowed as Qualifiers'!$A$1:$A$1896,'Allowed as Qualifiers'!$B$1:$B$1896,0) -> 1 | C11: =IF(B11=1,1,0)*IF(G11>0,1,0) -> 1 | D11: applies to part | E11: Ctxt | F11: Subject Modifier | G11: 1791730 | H11: =_xlfn.XLOOKUP(A11,'Diversity Analysis'!$A$2:$A$2366,'Diversity Analysis'!$F$2:$F$2366,"") -> 1662 | I11: 20.354618 | J11: 189.55654 | K11: =G11/1000000*J11 -> 339.63414 | R11: Meta | S11: =COUNTIF($F$3:$F$53,R11) -> 0 | T11: =COUNTIF($F$3:$F$306,R11) -> 18
A12: P3831 | B12: =_xlfn.XLOOKUP(A12,'Allowed as Qualifiers'!$A$1:$A$1896,'Allowed as Qualifiers'!$B$1:$B$1896,0) -> 1 | C12: =IF(B12=1,1,0)*IF(G12>0,1,0) -> 1 | D12: object of statement has role | E12: A | F12: Object/Subject Statement Relation | G12: 1953878 | H12: =_xlfn.XLOOKUP(A12,'Diversity Analysis'!$A$2:$A$2366,'Diversity Analysis'!$F$2:$F$2366,"") -> 923 | I12: 31.761936 | J12: 96.789859 | K12: =G12/1000000*J12 -> 189.11558 | R12: Sequence | S12: =COUNTIF($F$3:$F$53,R12) -> 3 | T12: =COUNTIF($F$3:$F$306,R12) -> 7
A13: P1013 | B13: =_xlfn.XLOOKUP(A13,'Allowed as Qualifiers'!$A$1:$A$1896,'Allowed as Qualifiers'!$B$1:$B$1896,0) -> 1 | C13: =IF(B13=1,1,0)*IF(G13>0,1,0) -> 1 | D13: criterion used | E13: A | F13: Sub-Property or Value | G13: 2174032 | H13: =_xlfn.XLOOKUP(A13,'Diversity Analysis'!$A$2:$A$2366,'Diversity Analysis'!$F$2:$F$2366,"") -> 464 | I13: 10.596544 | J13: 52.808107 | K13: =G13/1000000*J13 -> 114.80651 | M13: Sub-Property or Value indicator (population/are, opposite/criterion, | R13: Provenance | S13: =COUNTIF($F$3:$F$53,R13) -> 5 | T13: =COUNTIF($F$3:$F$306,R13) -> 12
A14: P577 | B14: =_xlfn.XLOOKUP(A14,'Allowed as Qualifiers'!$A$1:$A$1896,'Allowed as Qualifiers'!$B$1:$B$1896,0) -> 1 | C14: =IF(B14=1,1,0)*IF(G14>0,1,0) -> 1 | D14: publication date | E14: A | F14: External Object Description | G14: 2030479 | H14: =_xlfn.XLOOKUP(A14,'Diversity Analysis'!$A$2:$A$2366,'Diversity Analysis'!$F$2:$F$2366,"") -> 526 | I14: 5.3697342 | J14: 53.171989 | K14: =G14/1000000*J14 -> 107.96461 | M14: usage in cites word and published in is wrong | R14: Causality | S14: =COUNTIF($F$3:$F$53,R14) -> 1 | T14: =COUNTIF($F$3:$F$306,R14) -> 4
A15: P972 | B15: =_xlfn.XLOOKUP(A15,'Allowed as Qualifiers'!$A$1:$A$1896,'Allowed as Qualifiers'!$B$1:$B$1896,0) -> 1 | C15: =IF(B15=1,1,0)*IF(G15>0,1,0) -> 1 | D15: catalog | E15: Struct | F15: Structured Value | G15: 24051714 | H15: =_xlfn.XLOOKUP(A15,'Diversity Analysis'!$A$2:$A$2366,'Diversity Analysis'!$F$2:$F$2366,"") -> 60 | I15: 1.0265834 | J15: 4.3282113 | K15: =G15/1000000*J15 -> 104.1009 | M15: mandatory annotation for catalog_code | R15: Object/Subject Statement Relation | S15: =COUNTIF($F$3:$F$53,R15) -> 2 | T15: =COUNTIF($F$3:$F$306,R15) -> 5
A16: P1227 | B16: =_xlfn.XLOOKUP(A16,'Allowed as Qualifiers'!$A$1:$A$1896,'Allowed as Qualifiers'!$B$1:$B$1896,0) -> 1 | C16: =IF(B16=1,1,0)*IF(G16>0,1,0) -> 1 | D16: astronomical filter | E16: Struct | F16: Structured Value | G16: 33145675 | H16: =_xlfn.XLOOKUP(A16,'Diversity Analysis'!$A$2:$A$2366,'Diversity Analysis'!$F$2:$F$2366,"") -> 4 | I16: 1.0000175 | J16: 1.9226712 | K16: =G16/1000000*J16 -> 63.728236 | M16: mandatory for star magnitude & color index | R16: Sub-Property or Value | S16: =COUNTIF($F$3:$F$53,R16) -> 4 | T16: =COUNTIF($F$3:$F$306,R16) -> 9
A17: P2701 | B17: =_xlfn.XLOOKUP(A17,'Allowed as Qualifiers'!$A$1:$A$1896,'Allowed as Qualifiers'!$B$1:$B$1896,0) -> 1 | C17: =IF(B17=1,1,0)*IF(G17>0,1,0) -> 1 | D17: file format | E17: A | F17: External Object Description | G17: 3146867 | H17: =_xlfn.XLOOKUP(A17,'Diversity Analysis'!$A$2:$A$2366,'Diversity Analysis'!$F$2:$F$2366,"") -> 94 | I17: 1.131255 | J17: 11.368601 | K17: =G17/1000000*J17 -> 35.775477 | R17: External Object Description | S17: =COUNTIF($F$3:$F$53,R17) -> 11 | T17: =COUNTIF($F$3:$F$306,R17) -> 49
A18: P1001 | B18: =_xlfn.XLOOKUP(A18,'Allowed as Qualifiers'!$A$1:$A$1896,'Allowed as Qualifiers'!$B$1:$B$1896,0) -> 1 | C18: =IF(B18=1,1,0)*IF(G18>0,1,0) -> 1 | D18: applies to jurisdiction | E18: Ctxt | F18: Space | G18: 1433042 | H18: =_xlfn.XLOOKUP(A18,'Diversity Analysis'!$A$2:$A$2366,'Diversity Analysis'!$F$2:$F$2366,"") -> 364 | I18: 2.513847 | J18: 20.255587 | K18: =G18/1000000*J18 -> 29.027106 | R18: Other Additional | S18: =COUNTIF($F$3:$F$53,R18) -> 8 | T18: =COUNTIF($F$3:$F$306,R18) -> 155
A19: P2868 | B19: =_xlfn.XLOOKUP(A19,'Allowed as Qualifiers'!$A$1:$A$1896,'Allowed as Qualifiers'!$B$1:$B$1896,0) -> 1 | C19: =IF(B19=1,1,0)*IF(G19>0,1,0) -> 1 | D19: subject has role | E19: A | F19: Object/Subject Statement Relation | G19: 872919 | H19: =_xlfn.XLOOKUP(A19,'Diversity Analysis'!$A$2:$A$2366,'Diversity Analysis'!$F$2:$F$2366,"") -> 521 | I19: 10.812686 | J19: 31.810434 | K19: =G19/1000000*J19 -> 27.767933 | S19: =SUM(S5:S18) -> 50 | T19: =SUM(T5:T18) -> 300
A20: P7452 | B20: =_xlfn.XLOOKUP(A20,'Allowed as Qualifiers'!$A$1:$A$1896,'Allowed as Qualifiers'!$B$1:$B$1896,0) -> 1 | C20: =IF(B20=1,1,0)*IF(G20>0,1,0) -> 1 | D20: reason for preferred rank | E20: A | F20: Provenance | G20: 277968 | H20: =_xlfn.XLOOKUP(A20,'Diversity Analysis'!$A$2:$A$2366,'Diversity Analysis'!$F$2:$F$2366,"") -> 876 | I20: 9.4578249 | J20: 93.841605 | K20: =G20/1000000*J20 -> 26.084963
A21: P1480 | B21: =_xlfn.XLOOKUP(A21,'Allowed as Qualifiers'!$A$1:$A$1896,'Allowed as Qualifiers'!$B$1:$B$1896,0) -> 1 | C21: =IF(B21=1,1,0)*IF(G21>0,1,0) -> 1 | D21: sourcing circumstances | E21: E/U | F21: Epistemic | G21: 397143 | H21: =_xlfn.XLOOKUP(A21,'Diversity Analysis'!$A$2:$A$2366,'Diversity Analysis'!$F$2:$F$2366,"") -> 753 | I21: 7.5652949 | J21: 64.251495 | K21: =G21/1000000*J21 -> 25.517031 | M21: truth of statement, accuracy, reliability, confidence, precision, certainty, validity, 82% value = circa
A22: P2093 | B22: =_xlfn.XLOOKUP(A22,'Allowed as Qualifiers'!$A$1:$A$1896,'Allowed as Qualifiers'!$B$1:$B$1896,0) -> 1 | C22: =IF(B22=1,1,0)*IF(G22>0,1,0) -> 1 | D22: author name string | E22: A | F22: External Object Description | G22: 846447 | H22: =_xlfn.XLOOKUP(A22,'Diversity Analysis'!$A$2:$A$2366,'Diversity Analysis'!$F$2:$F$2366,"") -> 193 | I22: 2.1734145 | J22: 27.577817 | K22: =G22/1000000*J22 -> 23.343161
A23: P805 | B23: =_xlfn.XLOOKUP(A23,'Allowed as Qualifiers'!$A$1:$A$1896,'Allowed as Qualifiers'!$B$1:$B$1896,0) -> 1 | C23: =IF(B23=1,1,0)*IF(G23>0,1,0) -> 1 | D23: statement is subject of | E23: A | F23: Other Additional | G23: 665040 | H23: =_xlfn.XLOOKUP(A23,'Diversity Analysis'!$A$2:$A$2366,'Diversity Analysis'!$F$2:$F$2366,"") -> 614 | I23: 4.8361258 | J23: 32.659876 | K23: =G23/1000000*J23 -> 21.720124
A24: P642 | B24: =_xlfn.XLOOKUP(A24,'Allowed as Qualifiers'!$A$1:$A$1896,'Allowed as Qualifiers'!$B$1:$B$1896,0) -> 1 | C24: =IF(B24=1,1,0)*IF(G24>0,1,0) -> 1 | D24: of | F24: N/A | G24: 418350 | H24: =_xlfn.XLOOKUP(A24,'Diversity Analysis'!$A$2:$A$2366,'Diversity Analysis'!$F$2:$F$2366,"") -> 662 | I24: 8.2660494 | J24: 51.265861 | K24: =G24/1000000*J24 -> 21.447073 | M24: deprecated
A25: P1352 | B25: =_xlfn.XLOOKUP(A25,'Allowed as Qualifiers'!$A$1:$A$1896,'Allowed as Qualifiers'!$B$1:$B$1896,0) -> 1 | C25: =IF(B25=1,1,0)*IF(G25>0,1,0) -> 1 | D25: ranking | E25: A | F25: Other Additional | G25: 1089666 | H25: =_xlfn.XLOOKUP(A25,'Diversity Analysis'!$A$2:$A$2366,'Diversity Analysis'!$F$2:$F$2366,"") -> 89 | I25: 7.0075925 | J25: 19.131755 | K25: =G25/1000000*J25 -> 20.847223
A26: P478 | B26: =_xlfn.XLOOKUP(A26,'Allowed as Qualifiers'!$A$1:$A$1896,'Allowed as Qualifiers'!$B$1:$B$1896,0) -> 1 | C26: =IF(B26=1,1,0)*IF(G26>0,1,0) -> 1 | D26: volume | E26: A | F26: Sub-Property or Value | G26: 1075074 | H26: =_xlfn.XLOOKUP(A26,'Diversity Analysis'!$A$2:$A$2366,'Diversity Analysis'!$F$2:$F$2366,"") -> 199 | I26: 2.8254275 | J26: 14.614536 | K26: =G26/1000000*J26 -> 15.711707 | M26: for published in, with cites word = error
A27: P1552 | B27: =_xlfn.XLOOKUP(A27,'Allowed as Qualifiers'!$A$1:$A$1896,'Allowed as Qualifiers'!$B$1:$B$1896,0) -> 1 | C27: =IF(B27=1,1,0)*IF(G27>0,1,0) -> 1 | D27: has characteristic | E27: A | F27: External Object Description | G27: 210067 | H27: =_xlfn.XLOOKUP(A27,'Diversity Analysis'!$A$2:$A$2366,'Diversity Analysis'!$F$2:$F$2366,"") -> 747 | I27: 12.657377 | J27: 72.728797 | K27: =G27/1000000*J27 -> 15.27792
A28: P1326 | B28: =_xlfn.XLOOKUP(A28,'Allowed as Qualifiers'!$A$1:$A$1896,'Allowed as Qualifiers'!$B$1:$B$1896,0) -> 1 | C28: =IF(B28=1,1,0)*IF(G28>0,1,0) -> 1 | D28: latest date | E28: E/U | F28: Uncertainty Quantification | G28: 415023 | H28: =_xlfn.XLOOKUP(A28,'Diversity Analysis'!$A$2:$A$2366,'Diversity Analysis'!$F$2:$F$2366,"") -> 263 | I28: 3.6373913 | J28: 34.56331 | K28: =G28/1000000*J28 -> 14.344569 | M28: qualifier for date properties, indicates uncertainty
A29: P6954 | B29: =_xlfn.XLOOKUP(A29,'Allowed as Qualifiers'!$A$1:$A$1896,'Allowed as Qualifiers'!$B$1:$B$1896,0) -> 1 | C29: =IF(B29=1,1,0)*IF(G29>0,1,0) -> 1 | D29: online access status | E29: A | F29: External Object Description | G29: 1939603 | H29: =_xlfn.XLOOKUP(A29,'Diversity Analysis'!$A$2:$A$2366,'Diversity Analysis'!$F$2:$F$2366,"") -> 69 | I29: 1.0140949 | J29: 6.0812224 | K29: =G29/1000000*J29 -> 11.795157
A30: P304 | B30: =_xlfn.XLOOKUP(A30,'Allowed as Qualifiers'!$A$1:$A$1896,'Allowed as Qualifiers'!$B$1:$B$1896,0) -> 1 | C30: =IF(B30=1,1,0)*IF(G30>0,1,0) -> 1 | D30: page(s) | E30: A | F30: Sub-Property or Value | G30: 1479029 | H30: =_xlfn.XLOOKUP(A30,'Diversity Analysis'!$A$2:$A$2366,'Diversity Analysis'!$F$2:$F$2366,"") -> 204 | I30: 3.0792176 | J30: 7.9747331 | K30: =G30/1000000*J30 -> 11.794862 | M30: for published in, with cites word = error
A31: P2096 | B31: =_xlfn.XLOOKUP(A31,'Allowed as Qualifiers'!$A$1:$A$1896,'Allowed as Qualifiers'!$B$1:$B$1896,0) -> 1 | C31: =IF(B31=1,1,0)*IF(G31>0,1,0) -> 1 | D31: media legend | E31: A | F31: External Object Description | G31: 289612 | H31: =_xlfn.XLOOKUP(A31,'Diversity Analysis'!$A$2:$A$2366,'Diversity Analysis'!$F$2:$F$2366,"") -> 218 | I31: 1.5512387 | J31: 39.727214 | K31: =G31/1000000*J31 -> 11.505478 | M31: for several image … predicates
A32: P195 | B32: =_xlfn.XLOOKUP(A32,'Allowed as Qualifiers'!$A$1:$A$1896,'Allowed as Qualifiers'!$B$1:$B$1896,0) -> 1 | C32: =IF(B32=1,1,0)*IF(G32>0,1,0) -> 1 | D32: collection | E32: Struct | F32: Structured Value | G32: 1800053 | H32: =_xlfn.XLOOKUP(A32,'Diversity Analysis'!$A$2:$A$2366,'Diversity Analysis'!$F$2:$F$2366,"") -> 111 | I32: 1.2277708 | J32: 6.0430723 | K32: =G32/1000000*J32 -> 10.87785 | M32: mandatory annotation for inventory_number
A33: P400 | B33: =_xlfn.XLOOKUP(A33,'Allowed as Qualifiers'!$A$1:$A$1896,'Allowed as Qualifiers'!$B$1:$B$1896,0) -> 1 | C33: =IF(B33=1,1,0)*IF(G33>0,1,0) -> 1 | D33: platform | E33: A | F33: External Object Description | G33: 228447 | H33: =_xlfn.XLOOKUP(A33,'Diversity Analysis'!$A$2:$A$2366,'Diversity Analysis'!$F$2:$F$2366,"") -> 266 | I33: 17.246737 | J33: 47.385684 | K33: =G33/1000000*J33 -> 10.825117
A34: P2699 | B34: =_xlfn.XLOOKUP(A34,'Allowed as Qualifiers'!$A$1:$A$1896,'Allowed as Qualifiers'!$B$1:$B$1896,0) -> 1 | C34: =IF(B34=1,1,0)*IF(G34>0,1,0) -> 1 | D34: URL | E34: A | F34: Other Additional | G34: 352080 | H34: =_xlfn.XLOOKUP(A34,'Diversity Analysis'!$A$2:$A$2366,'Diversity Analysis'!$F$2:$F$2366,"") -> 460 | I34: 4.6664887 | J34: 30.639212 | K34: =G34/1000000*J34 -> 10.787454
A35: P6259 | B35: =_xlfn.XLOOKUP(A35,'Allowed as Qualifiers'!$A$1:$A$1896,'Allowed as Qualifiers'!$B$1:$B$1896,0) -> 1 | C35: =IF(B35=1,1,0)*IF(G35>0,1,0) -> 1 | D35: epoch | E35: Struct | F35: Structured Value | G35: 987965 | H35: =_xlfn.XLOOKUP(A35,'Diversity Analysis'!$A$2:$A$2366,'Diversity Analysis'!$F$2:$F$2366,"") -> 19 | I35: 10.012824 | J35: 9.9223814 | K35: =G35/1000000*J35 -> 9.8029655
A36: P1534 | B36: =_xlfn.XLOOKUP(A36,'Allowed as Qualifiers'!$A$1:$A$1896,'Allowed as Qualifiers'!$B$1:$B$1896,0) -> 1 | C36: =IF(B36=1,1,0)*IF(G36>0,1,0) -> 1 | D36: end cause | E36: A | F36: Causality | G36: 204973 | H36: =_xlfn.XLOOKUP(A36,'Diversity Analysis'!$A$2:$A$2366,'Diversity Analysis'!$F$2:$F$2366,"") -> 339 | I36: 8.2297455 | J36: 43.037466 | K36: =G36/1000000*J36 -> 8.8215186
A37: P1319 | B37: =_xlfn.XLOOKUP(A37,'Allowed as Qualifiers'!$A$1:$A$1896,'Allowed as Qualifiers'!$B$1:$B$1896,0) -> 1 | C37: =IF(B37=1,1,0)*IF(G37>0,1,0) -> 1 | D37: earliest date | E37: E/U | F37: Uncertainty Quantification | G37: 365280 | H37: =_xlfn.XLOOKUP(A37,'Diversity Analysis'!$A$2:$A$2366,'Diversity Analysis'!$F$2:$F$2366,"") -> 243 | I37: 2.6108141 | J37: 22.643891 | K37: =G37/1000000*J37 -> 8.2713603 | M37: qualifier for date properties, indicates uncertainty
A38: P1057 | B38: =_xlfn.XLOOKUP(A38,'Allowed as Qualifiers'!$A$1:$A$1896,'Allowed as Qualifiers'!$B$1:$B$1896,0) -> 1 | C38: =IF(B38=1,1,0)*IF(G38>0,1,0) -> 1 | D38: chromosome | E38: Struct | F38: Structured Value | G38: 2776319 | H38: =_xlfn.XLOOKUP(A38,'Diversity Analysis'!$A$2:$A$2366,'Diversity Analysis'!$F$2:$F$2366,"") -> 10 | I38: 2.9742531 | J38: 2.9780684 | K38: =G38/1000000*J38 -> 8.2680679
A39: P3744 | B39: =_xlfn.XLOOKUP(A39,'Allowed as Qualifiers'!$A$1:$A$1896,'Allowed as Qualifiers'!$B$1:$B$1896,0) -> 1 | C39: =IF(B39=1,1,0)*IF(G39>0,1,0) -> 1 | D39: number of subscribers | E39: A | F39: External Object Description | G39: 341490 | H39: =_xlfn.XLOOKUP(A39,'Diversity Analysis'!$A$2:$A$2366,'Diversity Analysis'!$F$2:$F$2366,"") -> 128 | I39: 3.2567672 | J39: 23.155297 | K39: =G39/1000000*J39 -> 7.9073024
A40: P155 | B40: =_xlfn.XLOOKUP(A40,'Allowed as Qualifiers'!$A$1:$A$1896,'Allowed as Qualifiers'!$B$1:$B$1896,0) -> 1 | C40: =IF(B40=1,1,0)*IF(G40>0,1,0) -> 1 | D40: follows | E40: A | F40: Sequence | G40: 1030678 | H40: =_xlfn.XLOOKUP(A40,'Diversity Analysis'!$A$2:$A$2366,'Diversity Analysis'!$F$2:$F$2366,"") -> 164 | I40: 3.5201501 | J40: 7.5203741 | K40: =G40/1000000*J40 -> 7.7510841
A41: P156 | B41: =_xlfn.XLOOKUP(A41,'Allowed as Qualifiers'!$A$1:$A$1896,'Allowed as Qualifiers'!$B$1:$B$1896,0) -> 1 | C41: =IF(B41=1,1,0)*IF(G41>0,1,0) -> 1 | D41: followed by | E41: A | F41: Sequence | G41: 1019627 | H41: =_xlfn.XLOOKUP(A41,'Diversity Analysis'!$A$2:$A$2366,'Diversity Analysis'!$F$2:$F$2366,"") -> 153 | I41: 3.4905436 | J41: 7.1021074 | K41: =G41/1000000*J41 -> 7.2415004
A42: P1476 | B42: =_xlfn.XLOOKUP(A42,'Allowed as Qualifiers'!$A$1:$A$1896,'Allowed as Qualifiers'!$B$1:$B$1896,0) -> 1 | C42: =IF(B42=1,1,0)*IF(G42>0,1,0) -> 1 | D42: title | E42: A | F42: External Object Description | G42: 164067 | H42: =_xlfn.XLOOKUP(A42,'Diversity Analysis'!$A$2:$A$2366,'Diversity Analysis'!$F$2:$F$2366,"") -> 611 | I42: 14.924221 | J42: 42.650017 | K42: =G42/1000000*J42 -> 6.9974604
A43: P1264 | B43: =_xlfn.XLOOKUP(A43,'Allowed as Qualifiers'!$A$1:$A$1896,'Allowed as Qualifiers'!$B$1:$B$1896,0) -> 1 | C43: =IF(B43=1,1,0)*IF(G43>0,1,0) -> 1 | D43: valid in period | E43: Ctxt | F43: Time | G43: 767714 | H43: =_xlfn.XLOOKUP(A43,'Diversity Analysis'!$A$2:$A$2366,'Diversity Analysis'!$F$2:$F$2366,"") -> 273 | I43: 1.2888555 | J43: 8.9410163 | K43: =G43/1000000*J43 -> 6.8641434
A44: P276 | B44: =_xlfn.XLOOKUP(A44,'Allowed as Qualifiers'!$A$1:$A$1896,'Allowed as Qualifiers'!$B$1:$B$1896,0) -> 1 | C44: =IF(B44=1,1,0)*IF(G44>0,1,0) -> 1 | D44: location | E44: A | F44: Other Additional | G44: 206656 | H44: =_xlfn.XLOOKUP(A44,'Diversity Analysis'!$A$2:$A$2366,'Diversity Analysis'!$F$2:$F$2366,"") -> 539 | I44: 17.529991 | J44: 33.061605 | K44: =G44/1000000*J44 -> 6.832379 | M44: ok for 'significant event', dubious for 'historic county'
A45: P9675 | B45: =_xlfn.XLOOKUP(A45,'Allowed as Qualifiers'!$A$1:$A$1896,'Allowed as Qualifiers'!$B$1:$B$1896,0) -> 1 | C45: =IF(B45=1,1,0)*IF(G45>0,1,0) -> 1 | D45: MediaWiki page ID | E45: A | F45: External Object Description | G45: 186329 | H45: =_xlfn.XLOOKUP(A45,'Diversity Analysis'!$A$2:$A$2366,'Diversity Analysis'!$F$2:$F$2366,"") -> 65 | I45: 4.1696114 | J45: 34.961074 | K45: =G45/1000000*J45 -> 6.514262 | M45: except <described by source>
A46: P1114 | B46: =_xlfn.XLOOKUP(A46,'Allowed as Qualifiers'!$A$1:$A$1896,'Allowed as Qualifiers'!$B$1:$B$1896,0) -> 1 | C46: =IF(B46=1,1,0)*IF(G46>0,1,0) -> 1 | D46: quantity | E46: Struct | F46: Structured Value | G46: 235469 | H46: =_xlfn.XLOOKUP(A46,'Diversity Analysis'!$A$2:$A$2366,'Diversity Analysis'!$F$2:$F$2366,"") -> 256 | I46: 7.1752365 | J46: 25.435562 | K46: =G46/1000000*J46 -> 5.9892862
A47: P813 | B47: =_xlfn.XLOOKUP(A47,'Allowed as Qualifiers'!$A$1:$A$1896,'Allowed as Qualifiers'!$B$1:$B$1896,0) -> 1 | C47: =IF(B47=1,1,0)*IF(G47>0,1,0) -> 1 | D47: retrieved | E47: A | F47: Provenance | G47: 130136 | H47: =_xlfn.XLOOKUP(A47,'Diversity Analysis'!$A$2:$A$2366,'Diversity Analysis'!$F$2:$F$2366,"") -> 879 | I47: 13.436908 | J47: 43.660635 | K47: =G47/1000000*J47 -> 5.6818205
A48: P1351 | B48: =_xlfn.XLOOKUP(A48,'Allowed as Qualifiers'!$A$1:$A$1896,'Allowed as Qualifiers'!$B$1:$B$1896,0) -> 1 | C48: =IF(B48=1,1,0)*IF(G48>0,1,0) -> 1 | D48: number of points/goals/set scored | E48: A | F48: Other Additional | G48: 878502 | H48: =_xlfn.XLOOKUP(A48,'Diversity Analysis'!$A$2:$A$2366,'Diversity Analysis'!$F$2:$F$2366,"") -> 27 | I48: 2.224831 | J48: 6.181026 | K48: =G48/1000000*J48 -> 5.4300437
A49: P1065 | B49: =_xlfn.XLOOKUP(A49,'Allowed as Qualifiers'!$A$1:$A$1896,'Allowed as Qualifiers'!$B$1:$B$1896,0) -> 1 | C49: =IF(B49=1,1,0)*IF(G49>0,1,0) -> 1 | D49: archive URL | E49: A | F49: Other Additional | G49: 131627 | H49: =_xlfn.XLOOKUP(A49,'Diversity Analysis'!$A$2:$A$2366,'Diversity Analysis'!$F$2:$F$2366,"") -> 365 | I49: 3.9560754 | J49: 40.445055 | K49: =G49/1000000*J49 -> 5.3236613
A50: P659 | B50: =_xlfn.XLOOKUP(A50,'Allowed as Qualifiers'!$A$1:$A$1896,'Allowed as Qualifiers'!$B$1:$B$1896,0) -> 1 | C50: =IF(B50=1,1,0)*IF(G50>0,1,0) -> 1 | D50: genomic assembly | E50: Struct | F50: Structured Value | G50: 1489227 | H50: =_xlfn.XLOOKUP(A50,'Diversity Analysis'!$A$2:$A$2366,'Diversity Analysis'!$F$2:$F$2366,"") -> 7 | I50: 3.2648107 | J50: 3.4071753 | K50: =G50/1000000*J50 -> 5.0740574
A51: P4390 | B51: =_xlfn.XLOOKUP(A51,'Allowed as Qualifiers'!$A$1:$A$1896,'Allowed as Qualifiers'!$B$1:$B$1896,0) -> 1 | C51: =IF(B51=1,1,0)*IF(G51>0,1,0) -> 1 | D51: mapping relation type | E51: A | F51: Sub-Property or Value | G51: 228972 | H51: =_xlfn.XLOOKUP(A51,'Diversity Analysis'!$A$2:$A$2366,'Diversity Analysis'!$F$2:$F$2366,"") -> 195 | I51: 4.356392 | J51: 21.291614 | K51: =G51/1000000*J51 -> 4.8751835
A52: P703 | B52: =_xlfn.XLOOKUP(A52,'Allowed as Qualifiers'!$A$1:$A$1896,'Allowed as Qualifiers'!$B$1:$B$1896,0) -> 1 | C52: =IF(B52=1,1,0)*IF(G52>0,1,0) -> 1 | D52: found in taxon | E52: A | F52: Other Additional | G52: 4361971 | H52: =_xlfn.XLOOKUP(A52,'Diversity Analysis'!$A$2:$A$2366,'Diversity Analysis'!$F$2:$F$2366,"") -> 20 | I52: 1.0007117 | J52: 1.0385861 | K52: =G52/1000000*J52 -> 4.5302822 | M52: seems to be redundant
A53: P625 | B53: =_xlfn.XLOOKUP(A53,'Allowed as Qualifiers'!$A$1:$A$1896,'Allowed as Qualifiers'!$B$1:$B$1896,0) -> 1 | C53: =IF(B53=1,1,0)*IF(G53>0,1,0) -> 1 | D53: coordinate location | E53: A | F53: Other Additional | G53: 326248 | H53: =_xlfn.XLOOKUP(A53,'Diversity Analysis'!$A$2:$A$2366,'Diversity Analysis'!$F$2:$F$2366,"") -> 153 | I53: 4.7561544 | J53: 12.952183 | K53: =G53/1000000*J53 -> 4.2256238
A54: P1366 | B54: =_xlfn.XLOOKUP(A54,'Allowed as Qualifiers'!$A$1:$A$1896,'Allowed as Qualifiers'!$B$1:$B$1896,0) -> 1 | C54: =IF(B54=1,1,0)*IF(G54>0,1,0) -> 1 | D54: replaced by | E54: A | F54: Sequence | G54: 237616 | H54: =_xlfn.XLOOKUP(A54,'Diversity Analysis'!$A$2:$A$2366,'Diversity Analysis'!$F$2:$F$2366,"") -> 151 | I54: 1.4355094 | J54: 17.21274 | K54: =G54/1000000*J54 -> 4.0900224
A55: P54 | B55: =_xlfn.XLOOKUP(A55,'Allowed as Qualifiers'!$A$1:$A$1896,'Allowed as Qualifiers'!$B$1:$B$1896,0) -> 1 | C55: =IF(B55=1,1,0)*IF(G55>0,1,0) -> 1 | D55: member of sports team | E55: A | F55: Other Additional | G55: 351931 | H55: =_xlfn.XLOOKUP(A55,'Diversity Analysis'!$A$2:$A$2366,'Diversity Analysis'!$F$2:$F$2366,"") -> 42 | I55: 2.5015284 | J55: 11.147536 | K55: =G55/1000000*J55 -> 3.9231636
A56: P3274 | B56: =_xlfn.XLOOKUP(A56,'Allowed as Qualifiers'!$A$1:$A$1896,'Allowed as Qualifiers'!$B$1:$B$1896,0) -> 1 | C56: =IF(B56=1,1,0)*IF(G56>0,1,0) -> 1 | D56: content deliverer | E56: A | F56: External Object Description | G56: 1010957 | H56: =_xlfn.XLOOKUP(A56,'Diversity Analysis'!$A$2:$A$2366,'Diversity Analysis'!$F$2:$F$2366,"") -> 42 | I56: 1.0681779 | J56: 3.7341435 | K56: =G56/1000000*J56 -> 3.7750585
A57: P2241 | B57: =_xlfn.XLOOKUP(A57,'Allowed as Qualifiers'!$A$1:$A$1896,'Allowed as Qualifiers'!$B$1:$B$1896,0) -> 1 | C57: =IF(B57=1,1,0)*IF(G57>0,1,0) -> 1 | D57: reason for deprecated rank | E57: A | F57: Provenance | G57: 64728 | H57: =_xlfn.XLOOKUP(A57,'Diversity Analysis'!$A$2:$A$2366,'Diversity Analysis'!$F$2:$F$2366,"") -> 487 | I57: 1.72401 | J57: 54.421838 | K57: =G57/1000000*J57 -> 3.5226167
A58: P958 | B58: =_xlfn.XLOOKUP(A58,'Allowed as Qualifiers'!$A$1:$A$1896,'Allowed as Qualifiers'!$B$1:$B$1896,0) -> 1 | C58: =IF(B58=1,1,0)*IF(G58>0,1,0) -> 1 | D58: section, verse, paragraph, or clause | E58: A | F58: Sub-Property or Value | G58: 177939 | H58: =_xlfn.XLOOKUP(A58,'Diversity Analysis'!$A$2:$A$2366,'Diversity Analysis'!$F$2:$F$2366,"") -> 150 | I58: 1.6833777 | J58: 19.569227 | K58: =G58/1000000*J58 -> 3.4821287
A59: P2937 | B59: =_xlfn.XLOOKUP(A59,'Allowed as Qualifiers'!$A$1:$A$1896,'Allowed as Qualifiers'!$B$1:$B$1896,0) -> 1 | C59: =IF(B59=1,1,0)*IF(G59>0,1,0) -> 1 | D59: parliamentary term | E59: Ctxt | F59: Time | G59: 562621 | H59: =_xlfn.XLOOKUP(A59,'Diversity Analysis'!$A$2:$A$2366,'Diversity Analysis'!$F$2:$F$2366,"") -> 48 | I59: 1.185676 | J59: 6.1218882 | K59: =G59/1000000*J59 -> 3.4443029
A60: P437 | B60: =_xlfn.XLOOKUP(A60,'Allowed as Qualifiers'!$A$1:$A$1896,'Allowed as Qualifiers'!$B$1:$B$1896,0) -> 1 | C60: =IF(B60=1,1,0)*IF(G60>0,1,0) -> 1 | D60: distribution format | E60: A | F60: External Object Description | G60: 208600 | H60: =_xlfn.XLOOKUP(A60,'Diversity Analysis'!$A$2:$A$2366,'Diversity Analysis'!$F$2:$F$2366,"") -> 193 | I60: 1.8096134 | J60: 16.091341 | K60: =G60/1000000*J60 -> 3.3566537
A61: P1539 | B61: =_xlfn.XLOOKUP(A61,'Allowed as Qualifiers'!$A$1:$A$1896,'Allowed as Qualifiers'!$B$1:$B$1896,0) -> 1 | C61: =IF(B61=1,1,0)*IF(G61>0,1,0) -> 1 | D61: female population | E61: A | F61: Other Additional | G61: 458218 | H61: =_xlfn.XLOOKUP(A61,'Diversity Analysis'!$A$2:$A$2366,'Diversity Analysis'!$F$2:$F$2366,"") -> 20 | I61: 5.7168067 | J61: 6.8133659 | K61: =G61/1000000*J61 -> 3.1220069
A62: P2561 | B62: =_xlfn.XLOOKUP(A62,'Allowed as Qualifiers'!$A$1:$A$1896,'Allowed as Qualifiers'!$B$1:$B$1896,0) -> 1 | C62: =IF(B62=1,1,0)*IF(G62>0,1,0) -> 1 | D62: name | E62: A | F62: External Object Description | G62: 313547 | H62: =_xlfn.XLOOKUP(A62,'Diversity Analysis'!$A$2:$A$2366,'Diversity Analysis'!$F$2:$F$2366,"") -> 284 | I62: 1.1008069 | J62: 9.3166231 | K62: =G62/1000000*J62 -> 2.9211992 | M62: used with 'has facility' to name a specific facility designated by the French sport venue ID qalifier
A63: P131 | B63: =_xlfn.XLOOKUP(A63,'Allowed as Qualifiers'!$A$1:$A$1896,'Allowed as Qualifiers'!$B$1:$B$1896,0) -> 1 | C63: =IF(B63=1,1,0)*IF(G63>0,1,0) -> 1 | D63: located in the administrative territorial entity | E63: A | F63: Other Additional | G63: 230362 | H63: =_xlfn.XLOOKUP(A63,'Diversity Analysis'!$A$2:$A$2366,'Diversity Analysis'!$F$2:$F$2366,"") -> 321 | I63: 13.989469 | J63: 12.645143 | K63: =G63/1000000*J63 -> 2.9129603 | M63: =+ redundant use or misuse
A64: P17 | B64: =_xlfn.XLOOKUP(A64,'Allowed as Qualifiers'!$A$1:$A$1896,'Allowed as Qualifiers'!$B$1:$B$1896,0) -> 1 | C64: =IF(B64=1,1,0)*IF(G64>0,1,0) -> 1 | D64: country | E64: Ctxt | F64: Space | G64: 125594 | H64: =_xlfn.XLOOKUP(A64,'Diversity Analysis'!$A$2:$A$2366,'Diversity Analysis'!$F$2:$F$2366,"") -> 447 | I64: 13.150297 | J64: 22.80453 | K64: =G64/1000000*J64 -> 2.8641122 | M64: Multiple categories: 1. wrong, 2. validity, 3. ext obj
A65: P973 | B65: =_xlfn.XLOOKUP(A65,'Allowed as Qualifiers'!$A$1:$A$1896,'Allowed as Qualifiers'!$B$1:$B$1896,0) -> 1 | C65: =IF(B65=1,1,0)*IF(G65>0,1,0) -> 1 | D65: described at URL | E65: A | F65: External Object Description | G65: 328877 | H65: =_xlfn.XLOOKUP(A65,'Diversity Analysis'!$A$2:$A$2366,'Diversity Analysis'!$F$2:$F$2366,"") -> 199 | I65: 1.9589525 | J65: 8.3402039 | K65: =G65/1000000*J65 -> 2.7429013
A66: P1540 | B66: =_xlfn.XLOOKUP(A66,'Allowed as Qualifiers'!$A$1:$A$1896,'Allowed as Qualifiers'!$B$1:$B$1896,0) -> 1 | C66: =IF(B66=1,1,0)*IF(G66>0,1,0) -> 1 | D66: male population | E66: A | F66: Other Additional | G66: 450122 | H66: =_xlfn.XLOOKUP(A66,'Diversity Analysis'!$A$2:$A$2366,'Diversity Analysis'!$F$2:$F$2366,"") -> 18 | I66: 5.3030609 | J66: 6.0552119 | K66: =G66/1000000*J66 -> 2.7255841 | M66: Sub-Property or Value value
A67: P5102 | B67: =_xlfn.XLOOKUP(A67,'Allowed as Qualifiers'!$A$1:$A$1896,'Allowed as Qualifiers'!$B$1:$B$1896,0) -> 1 | C67: =IF(B67=1,1,0)*IF(G67>0,1,0) -> 1 | D67: nature of statement | E67: E/U | F67: Epistemic | G67: 44203 | H67: =_xlfn.XLOOKUP(A67,'Diversity Analysis'!$A$2:$A$2366,'Diversity Analysis'!$F$2:$F$2366,"") -> 674 | I67: 42.342738 | J67: 60.646979 | K67: =G67/1000000*J67 -> 2.6807784
A68: P1365 | B68: =_xlfn.XLOOKUP(A68,'Allowed as Qualifiers'!$A$1:$A$1896,'Allowed as Qualifiers'!$B$1:$B$1896,0) -> 1 | C68: =IF(B68=1,1,0)*IF(G68>0,1,0) -> 1 | D68: replaces | E68: A | F68: Sequence | G68: 264616 | H68: =_xlfn.XLOOKUP(A68,'Diversity Analysis'!$A$2:$A$2366,'Diversity Analysis'!$F$2:$F$2366,"") -> 161 | I68: 1.3504657 | J68: 8.5323956 | K68: =G68/1000000*J68 -> 2.2578084
A69: P2047 | B69: =_xlfn.XLOOKUP(A69,'Allowed as Qualifiers'!$A$1:$A$1896,'Allowed as Qualifiers'!$B$1:$B$1896,0) -> 1 | C69: =IF(B69=1,1,0)*IF(G69>0,1,0) -> 1 | D69: duration | E69: A | F69: Other Additional | G69: 97288 | H69: =_xlfn.XLOOKUP(A69,'Diversity Analysis'!$A$2:$A$2366,'Diversity Analysis'!$F$2:$F$2366,"") -> 181 | I69: 3.371767 | J69: 22.641696 | K69: =G69/1000000*J69 -> 2.2027653
A70: P2378 | B70: =_xlfn.XLOOKUP(A70,'Allowed as Qualifiers'!$A$1:$A$1896,'Allowed as Qualifiers'!$B$1:$B$1896,0) -> 1 | C70: =IF(B70=1,1,0)*IF(G70>0,1,0) -> 1 | D70: issued by | E70: A | F70: External Object Description | G70: 210402 | H70: =_xlfn.XLOOKUP(A70,'Diversity Analysis'!$A$2:$A$2366,'Diversity Analysis'!$F$2:$F$2366,"") -> 72 | I70: 2.4473306 | J70: 9.7967465 | K70: =G70/1000000*J70 -> 2.0612551
A71: P6552 | B71: =_xlfn.XLOOKUP(A71,'Allowed as Qualifiers'!$A$1:$A$1896,'Allowed as Qualifiers'!$B$1:$B$1896,0) -> 1 | C71: =IF(B71=1,1,0)*IF(G71>0,1,0) -> 1 | D71: X numeric user ID | E71: A | F71: Other Additional | G71: 946718 | H71: =_xlfn.XLOOKUP(A71,'Diversity Analysis'!$A$2:$A$2366,'Diversity Analysis'!$F$2:$F$2366,"") -> 9 | I71: 1.9627565 | J71: 2.1609965 | K71: =G71/1000000*J71 -> 2.0458543
A72: P1350 | B72: =_xlfn.XLOOKUP(A72,'Allowed as Qualifiers'!$A$1:$A$1896,'Allowed as Qualifiers'!$B$1:$B$1896,0) -> 1 | C72: =IF(B72=1,1,0)*IF(G72>0,1,0) -> 1 | D72: number of matches played/races/starts | E72: A | F72: Other Additional | G72: 757578 | H72: =_xlfn.XLOOKUP(A72,'Diversity Analysis'!$A$2:$A$2366,'Diversity Analysis'!$F$2:$F$2366,"") -> 18 | I72: 1.5958764 | J72: 2.6884269 | K72: =G72/1000000*J72 -> 2.0366931
A73: P3740 | B73: =_xlfn.XLOOKUP(A73,'Allowed as Qualifiers'!$A$1:$A$1896,'Allowed as Qualifiers'!$B$1:$B$1896,0) -> 1 | C73: =IF(B73=1,1,0)*IF(G73>0,1,0) -> 1 | D73: number of works | E73: A | F73: External Object Description | G73: 188545 | H73: =_xlfn.XLOOKUP(A73,'Diversity Analysis'!$A$2:$A$2366,'Diversity Analysis'!$F$2:$F$2366,"") -> 104 | I73: 3.8615695 | J73: 10.3927 | K73: =G73/1000000*J73 -> 1.9594916
A74: P3005 | B74: =_xlfn.XLOOKUP(A74,'Allowed as Qualifiers'!$A$1:$A$1896,'Allowed as Qualifiers'!$B$1:$B$1896,0) -> 1 | C74: =IF(B74=1,1,0)*IF(G74>0,1,0) -> 1 | D74: valid in place | E74: Ctxt | F74: Space | G74: 106208 | H74: =_xlfn.XLOOKUP(A74,'Diversity Analysis'!$A$2:$A$2366,'Diversity Analysis'!$F$2:$F$2366,"") -> 325 | I74: 5.2332463 | J74: 18.360889 | K74: =G74/1000000*J74 -> 1.9500733
A75: P3680 | B75: =_xlfn.XLOOKUP(A75,'Allowed as Qualifiers'!$A$1:$A$1896,'Allowed as Qualifiers'!$B$1:$B$1896,0) -> 1 | C75: =IF(B75=1,1,0)*IF(G75>0,1,0) -> 1 | D75: statement supported by | E75: A | F75: Provenance | G75: 170398 | H75: =_xlfn.XLOOKUP(A75,'Diversity Analysis'!$A$2:$A$2366,'Diversity Analysis'!$F$2:$F$2366,"") -> 342 | I75: 4.6673039 | J75: 11.363891 | K75: =G75/1000000*J75 -> 1.9363843
A76: P613 | B76: =_xlfn.XLOOKUP(A76,'Allowed as Qualifiers'!$A$1:$A$1896,'Allowed as Qualifiers'!$B$1:$B$1896,0) -> 1 | C76: =IF(B76=1,1,0)*IF(G76>0,1,0) -> 1 | D76: OS grid reference | E76: A | F76: External Object Description | G76: 203351 | H76: =_xlfn.XLOOKUP(A76,'Diversity Analysis'!$A$2:$A$2366,'Diversity Analysis'!$F$2:$F$2366,"") -> 36 | I76: 4.059584 | J76: 9.5027756 | K76: =G76/1000000*J76 -> 1.9323989
A77: P512 | B77: =_xlfn.XLOOKUP(A77,'Allowed as Qualifiers'!$A$1:$A$1896,'Allowed as Qualifiers'!$B$1:$B$1896,0) -> 1 | C77: =IF(B77=1,1,0)*IF(G77>0,1,0) -> 1 | D77: academic degree | E77: A | F77: Other Additional | G77: 1024590 | H77: =_xlfn.XLOOKUP(A77,'Diversity Analysis'!$A$2:$A$2366,'Diversity Analysis'!$F$2:$F$2366,"") -> 39 | I77: 1.0099266 | J77: 1.7147899 | K77: =G77/1000000*J77 -> 1.7569565
A78: P217 | B78: =_xlfn.XLOOKUP(A78,'Allowed as Qualifiers'!$A$1:$A$1896,'Allowed as Qualifiers'!$B$1:$B$1896,0) -> 1 | C78: =IF(B78=1,1,0)*IF(G78>0,1,0) -> 1 | D78: inventory number | E78: Struct | F78: Structured Value | G78: 246398 | H78: =_xlfn.XLOOKUP(A78,'Diversity Analysis'!$A$2:$A$2366,'Diversity Analysis'!$F$2:$F$2366,"") -> 112 | I78: 3.1639651 | J78: 6.7306808 | K78: =G78/1000000*J78 -> 1.6584263
A79: P4970 | B79: =_xlfn.XLOOKUP(A79,'Allowed as Qualifiers'!$A$1:$A$1896,'Allowed as Qualifiers'!$B$1:$B$1896,0) -> 1 | C79: =IF(B79=1,1,0)*IF(G79>0,1,0) -> 1 | D79: alternative name | E79: A | F79: External Object Description | G79: 45659 | H79: =_xlfn.XLOOKUP(A79,'Diversity Analysis'!$A$2:$A$2366,'Diversity Analysis'!$F$2:$F$2366,"") -> 554 | I79: 25.291859 | J79: 34.764268 | K79: =G79/1000000*J79 -> 1.5873017
A80: P405 | B80: =_xlfn.XLOOKUP(A80,'Allowed as Qualifiers'!$A$1:$A$1896,'Allowed as Qualifiers'!$B$1:$B$1896,0) -> 1 | C80: =IF(B80=1,1,0)*IF(G80>0,1,0) -> 1 | D80: taxon author | E80: A | F80: Other Additional | G80: 1386734 | H80: =_xlfn.XLOOKUP(A80,'Diversity Analysis'!$A$2:$A$2366,'Diversity Analysis'!$F$2:$F$2366,"") -> 20 | I80: 1.0256752 | J80: 1.1237043 | K80: =G80/1000000*J80 -> 1.5582789 | M80: ~ only for taxon name
A81: P750 | B81: =_xlfn.XLOOKUP(A81,'Allowed as Qualifiers'!$A$1:$A$1896,'Allowed as Qualifiers'!$B$1:$B$1896,0) -> 1 | C81: =IF(B81=1,1,0)*IF(G81>0,1,0) -> 1 | D81: distributed by | E81: A | F81: External Object Description | G81: 283126 | H81: =_xlfn.XLOOKUP(A81,'Diversity Analysis'!$A$2:$A$2366,'Diversity Analysis'!$F$2:$F$2366,"") -> 77 | I81: 1.0841419 | J81: 5.4415421 | K81: =G81/1000000*J81 -> 1.5406421
A82: P768 | B82: =_xlfn.XLOOKUP(A82,'Allowed as Qualifiers'!$A$1:$A$1896,'Allowed as Qualifiers'!$B$1:$B$1896,0) -> 1 | C82: =IF(B82=1,1,0)*IF(G82>0,1,0) -> 1 | D82: electoral district | E82: A | F82: Other Additional | G82: 483301 | H82: =_xlfn.XLOOKUP(A82,'Diversity Analysis'!$A$2:$A$2366,'Diversity Analysis'!$F$2:$F$2366,"") -> 35 | I82: 2.2665955 | J82: 3.1011763 | K82: =G82/1000000*J82 -> 1.4988016
A83: P1358 | B83: =_xlfn.XLOOKUP(A83,'Allowed as Qualifiers'!$A$1:$A$1896,'Allowed as Qualifiers'!$B$1:$B$1896,0) -> 1 | C83: =IF(B83=1,1,0)*IF(G83>0,1,0) -> 1 | D83: points for | E83: A | F83: Other Additional | G83: 163937 | H83: =_xlfn.XLOOKUP(A83,'Diversity Analysis'!$A$2:$A$2366,'Diversity Analysis'!$F$2:$F$2366,"") -> 23 | I83: 4.9383151 | J83: 9.1002891 | K83: =G83/1000000*J83 -> 1.4918741
A84: P548 | B84: =_xlfn.XLOOKUP(A84,'Allowed as Qualifiers'!$A$1:$A$1896,'Allowed as Qualifiers'!$B$1:$B$1896,0) -> 1 | C84: =IF(B84=1,1,0)*IF(G84>0,1,0) -> 1 | D84: version type | E84: A | F84: Other Additional | G84: 452370 | H84: =_xlfn.XLOOKUP(A84,'Diversity Analysis'!$A$2:$A$2366,'Diversity Analysis'!$F$2:$F$2366,"") -> 46 | I84: 1.0304871 | J84: 3.1087133 | K84: =G84/1000000*J84 -> 1.4062886
A85: P574 | B85: =_xlfn.XLOOKUP(A85,'Allowed as Qualifiers'!$A$1:$A$1896,'Allowed as Qualifiers'!$B$1:$B$1896,0) -> 1 | C85: =IF(B85=1,1,0)*IF(G85>0,1,0) -> 1 | D85: year of publication of scientific name for taxon | E85: A | F85: Other Additional | G85: 1299083 | H85: =_xlfn.XLOOKUP(A85,'Diversity Analysis'!$A$2:$A$2366,'Diversity Analysis'!$F$2:$F$2366,"") -> 30 | I85: 1.0015571 | J85: 1.0806864 | K85: =G85/1000000*J85 -> 1.4039014 | M85: ~ only for taxon name
A86: P9688 | B86: =_xlfn.XLOOKUP(A86,'Allowed as Qualifiers'!$A$1:$A$1896,'Allowed as Qualifiers'!$B$1:$B$1896,0) -> 1 | C86: =IF(B86=1,1,0)*IF(G86>0,1,0) -> 1 | D86: author last names | E86: A | F86: External Object Description | G86: 296045 | H86: =_xlfn.XLOOKUP(A86,'Diversity Analysis'!$A$2:$A$2366,'Diversity Analysis'!$F$2:$F$2366,"") -> 11 | I86: 1.9601596 | J86: 4.6371253 | K86: =G86/1000000*J86 -> 1.3727978
A87: P2210 | B87: =_xlfn.XLOOKUP(A87,'Allowed as Qualifiers'!$A$1:$A$1896,'Allowed as Qualifiers'!$B$1:$B$1896,0) -> 1 | C87: =IF(B87=1,1,0)*IF(G87>0,1,0) -> 1 | D87: relative to | E87: Struct | F87: Structured Value | G87: 99408 | H87: =_xlfn.XLOOKUP(A87,'Diversity Analysis'!$A$2:$A$2366,'Diversity Analysis'!$F$2:$F$2366,"") -> 185 | I87: 4.3873341 | J87: 12.307013 | K87: =G87/1000000*J87 -> 1.2234155
A88: P9687 | B88: =_xlfn.XLOOKUP(A88,'Allowed as Qualifiers'!$A$1:$A$1896,'Allowed as Qualifiers'!$B$1:$B$1896,0) -> 1 | C88: =IF(B88=1,1,0)*IF(G88>0,1,0) -> 1 | D88: author given names | E88: A | F88: External Object Description | G88: 296035 | H88: =_xlfn.XLOOKUP(A88,'Diversity Analysis'!$A$2:$A$2366,'Diversity Analysis'!$F$2:$F$2366,"") -> 9 | I88: 1.9597636 | J88: 4.0212893 | K88: =G88/1000000*J88 -> 1.1904424
A89: P361 | B89: =_xlfn.XLOOKUP(A89,'Allowed as Qualifiers'!$A$1:$A$1896,'Allowed as Qualifiers'!$B$1:$B$1896,0) -> 1 | C89: =IF(B89=1,1,0)*IF(G89>0,1,0) -> 1 | D89: part of | E89: A | F89: Other Additional | G89: 96209 | H89: =_xlfn.XLOOKUP(A89,'Diversity Analysis'!$A$2:$A$2366,'Diversity Analysis'!$F$2:$F$2366,"") -> 336 | I89: 9.7088006 | J89: 12.102224 | K89: =G89/1000000*J89 -> 1.1643428
A90: P291 | B90: =_xlfn.XLOOKUP(A90,'Allowed as Qualifiers'!$A$1:$A$1896,'Allowed as Qualifiers'!$B$1:$B$1896,0) -> 1 | C90: =IF(B90=1,1,0)*IF(G90>0,1,0) -> 1 | D90: place of publication | E90: A | F90: Other Additional | G90: 167470 | H90: =_xlfn.XLOOKUP(A90,'Diversity Analysis'!$A$2:$A$2366,'Diversity Analysis'!$F$2:$F$2366,"") -> 130 | I90: 2.8661703 | J90: 6.7599555 | K90: =G90/1000000*J90 -> 1.1320897
A91: P106 | B91: =_xlfn.XLOOKUP(A91,'Allowed as Qualifiers'!$A$1:$A$1896,'Allowed as Qualifiers'!$B$1:$B$1896,0) -> 1 | C91: =IF(B91=1,1,0)*IF(G91>0,1,0) -> 1 | D91: occupation | E91: Struct | F91: Meta | G91: 145437 | H91: =_xlfn.XLOOKUP(A91,'Diversity Analysis'!$A$2:$A$2366,'Diversity Analysis'!$F$2:$F$2366,"") -> 162 | I91: 1.3606536 | J91: 7.5490104 | K91: =G91/1000000*J91 -> 1.0979054
A92: P433 | B92: =_xlfn.XLOOKUP(A92,'Allowed as Qualifiers'!$A$1:$A$1896,'Allowed as Qualifiers'!$B$1:$B$1896,0) -> 1 | C92: =IF(B92=1,1,0)*IF(G92>0,1,0) -> 1 | D92: issue | E92: A | F92: Sub-Property or Value | G92: 137111 | H92: =_xlfn.XLOOKUP(A92,'Diversity Analysis'!$A$2:$A$2366,'Diversity Analysis'!$F$2:$F$2366,"") -> 102 | I92: 1.3119384 | J92: 7.8076325 | K92: =G92/1000000*J92 -> 1.0705123
A93: P282 | B93: =_xlfn.XLOOKUP(A93,'Allowed as Qualifiers'!$A$1:$A$1896,'Allowed as Qualifiers'!$B$1:$B$1896,0) -> 1 | C93: =IF(B93=1,1,0)*IF(G93>0,1,0) -> 1 | D93: writing system | E93: A | F93: Other Additional | G93: 121038 | H93: =_xlfn.XLOOKUP(A93,'Diversity Analysis'!$A$2:$A$2366,'Diversity Analysis'!$F$2:$F$2366,"") -> 104 | I93: 5.5657892 | J93: 8.5454395 | K93: =G93/1000000*J93 -> 1.0343229
A94: P102 | B94: =_xlfn.XLOOKUP(A94,'Allowed as Qualifiers'!$A$1:$A$1896,'Allowed as Qualifiers'!$B$1:$B$1896,0) -> 1 | C94: =IF(B94=1,1,0)*IF(G94>0,1,0) -> 1 | D94: member of political party | E94: A | F94: Other Additional | G94: 157194 | H94: =_xlfn.XLOOKUP(A94,'Diversity Analysis'!$A$2:$A$2366,'Diversity Analysis'!$F$2:$F$2366,"") -> 42 | I94: 3.0154348 | J94: 6.4357445 | K94: =G94/1000000*J94 -> 1.0116604
A95: P5436 | B95: =_xlfn.XLOOKUP(A95,'Allowed as Qualifiers'!$A$1:$A$1896,'Allowed as Qualifiers'!$B$1:$B$1896,0) -> 1 | C95: =IF(B95=1,1,0)*IF(G95>0,1,0) -> 1 | D95: number of viewers/listeners | E95: A | F95: External Object Description | G95: 173299 | H95: =_xlfn.XLOOKUP(A95,'Diversity Analysis'!$A$2:$A$2366,'Diversity Analysis'!$F$2:$F$2366,"") -> 46 | I95: 1.9977941 | J95: 5.7889496 | K95: =G95/1000000*J95 -> 1.0032192
A96: P2676 | B96: =_xlfn.XLOOKUP(A96,'Allowed as Qualifiers'!$A$1:$A$1896,'Allowed as Qualifiers'!$B$1:$B$1896,0) -> 1 | C96: =IF(B96=1,1,0)*IF(G96>0,1,0) -> 1 | D96: rating certificate ID | E96: A | F96: Other Additional | G96: 51169 | H96: =_xlfn.XLOOKUP(A96,'Diversity Analysis'!$A$2:$A$2366,'Diversity Analysis'!$F$2:$F$2366,"") -> 29 | I96: 13.279242 | J96: 19.001389 | K96: =G96/1000000*J96 -> 0.97228205
A97: P275 | B97: =_xlfn.XLOOKUP(A97,'Allowed as Qualifiers'!$A$1:$A$1896,'Allowed as Qualifiers'!$B$1:$B$1896,0) -> 1 | C97: =IF(B97=1,1,0)*IF(G97>0,1,0) -> 1 | D97: copyright license | E97: A | F97: External Object Description | G97: 217795 | H97: =_xlfn.XLOOKUP(A97,'Diversity Analysis'!$A$2:$A$2366,'Diversity Analysis'!$F$2:$F$2366,"") -> 61 | I97: 1.4002726 | J97: 4.0328512 | K97: =G97/1000000*J97 -> 0.87833483
... A100: P5051 | B100: =_xlfn.XLOOKUP(A100,'Allowed as Qualifiers'!$A$1:$A$1896,'Allowed as Qualifiers'!$B$1:$B$1896,0) -> 1 | C100: =IF(B100=1,1,0)*IF(G100>0,1,0) -> 1 | D100: towards | E100: Struct | F100: Structured Value | G100: 203235 | H100: =_xlfn.XLOOKUP(A100,'Diversity Analysis'!$A$2:$A$2366,'Diversity Analysis'!$F$2:$F$2366,"") -> 26 | I100: 1.1611136 | J100: 4.0133914 | K100: =G100/1000000*J100 -> 0.8156616
A101: P1705 | B101: =_xlfn.XLOOKUP(A101,'Allowed as Qualifiers'!$A$1:$A$1896,'Allowed as Qualifiers'!$B$1:$B$1896,0) -> 1 | C101: =IF(B101=1,1,0)*IF(G101>0,1,0) -> 1 | D101: native label | E101: A | G101: 80881 | H101: =_xlfn.XLOOKUP(A101,'Diversity Analysis'!$A$2:$A$2366,'Diversity Analysis'!$F$2:$F$2366,"") -> 112 | I101: 1.2973675 | J101: 9.8769139 | K101: =G101/1000000*J101 -> 0.79885467 | M101: 'native label' not allowed to qualify 'cites work'
A102: P39 | B102: =_xlfn.XLOOKUP(A102,'Allowed as Qualifiers'!$A$1:$A$1896,'Allowed as Qualifiers'!$B$1:$B$1896,0) -> 1 | C102: =IF(B102=1,1,0)*IF(G102>0,1,0) -> 1 | D102: position held | E102: A | F102: Other Additional | G102: 89715 | H102: =_xlfn.XLOOKUP(A102,'Diversity Analysis'!$A$2:$A$2366,'Diversity Analysis'!$F$2:$F$2366,"") -> 161 | I102: 5.3690185 | J102: 8.5638192 | K102: =G102/1000000*J102 -> 0.76830304
...

Sheet Allowed as Qualifiers
A1: P263 | B1: 1
A2: P264 | B2: 1
A3: P275 | B3: 1
A4: P276 | B4: 1
A5: P281 | B5: 1
A6: P282 | B6: 1
A7: P287 | B7: 1
A8: P286 | B8: 1
A9: P289 | B9: 1
A10: P291 | B10: 1
A11: P296 | B11: 1
A12: P305 | B12: 1
... A1896: P248 | B1896: 1

Sheet Diversity Analysis
A1: Qualifer | B1: Name | C1: Frequency | D1: Sh. Diversity | E1: Sh. Prop. Diversity | F1: Abundance | G1: Importance Score
A2: P1545 | B2: series ordinal | C2: 198557380 | D2: 2.2972161 | E2: 60.986634 | F2: 592 | G2: 1.2109346e+10
A3: P1227 | B3: astronomical filter | C3: 33145675 | D3: 1.0000175 | E3: 1.9226712 | F3: 4 | G3: 63728236
A4: P972 | B4: catalog | C4: 24051714 | D4: 1.0265834 | E4: 4.3282113 | F4: 60 | G4: 1.041009e+08
A5: P1932 | B5: object named as | C5: 22167461 | D5: 1.6783922 | E5: 75.626808 | F5: 1096 | G5: 1.6764543e+09
A6: P585 | B6: point in time | C6: 14667663 | D6: 22.605733 | E6: 292.34028 | F6: 1510 | G6: 4.2879487e+09
A7: P580 | B7: start time | C7: 11563055 | D7: 24.126413 | E7: 300.22414 | F7: 1727 | G7: 3.4715082e+09
A8: P459 | B8: determination method or standard | C8: 9624947 | D8: 9.3376637 | E8: 75.433105 | F8: 358 | G8: 7.2603963e+08
A9: P1810 | B9: subject named as | C9: 6480845 | D9: 74.628448 | E9: 716.95669 | F9: 4409 | G9: 4.6464852e+09
A10: P582 | B10: end time | C10: 5440957 | D10: 16.736172 | E10: 216.79831 | F10: 1483 | G10: 1.1795903e+09
A11: P703 | B11: found in taxon | C11: 4361971 | D11: 1.0007117 | E11: 1.0385861 | F11: 20 | G11: 4530282.2
A12: P2701 | B12: file format | C12: 3146867 | D12: 1.131255 | E12: 11.368601 | F12: 94 | G12: 35775477
A13: P1057 | B13: chromosome | C13: 2776319 | D13: 2.9742531 | E13: 2.9780684 | F13: 10 | G13: 8268067.9
... A2366: P8275 | B2366: position in biological sequence | C2366: 1 | D2366: 1 | E2366: 1 | F2366: 1 | G2366: 1

Sheet Distribution in Categories
C5: Category | D5: In Top 50 | E5: In Top 300
C6: Time | D6: =COUNTIF('Qualifier_Analysis_2025-01-01'!$F$3:$F$53,C6) -> 4 | E6: =COUNTIF('Qualifier_Analysis_2025-01-01'!$F$3:$F$306,C6) -> 8
C7: Space | D7: =COUNTIF('Qualifier_Analysis_2025-01-01'!$F$3:$F$53,C7) -> 1 | E7: =COUNTIF('Qualifier_Analysis_2025-01-01'!$F$3:$F$306,C7) -> 4
C8: Subject Modifier | D8: =COUNTIF('Qualifier_Analysis_2025-01-01'!$F$3:$F$53,C8) -> 1 | E8: =COUNTIF('Qualifier_Analysis_2025-01-01'!$F$3:$F$306,C8) -> 4
C9: Epistemic | D9: =COUNTIF('Qualifier_Analysis_2025-01-01'!$F$3:$F$53,C9) -> 1 | E9: =COUNTIF('Qualifier_Analysis_2025-01-01'!$F$3:$F$306,C9) -> 3
C10: Uncertainty Quantification | D10: =COUNTIF('Qualifier_Analysis_2025-01-01'!$F$3:$F$53,C10) -> 2 | E10: =COUNTIF('Qualifier_Analysis_2025-01-01'!$F$3:$F$306,C10) -> 5
C11: Structured Value | D11: =COUNTIF('Qualifier_Analysis_2025-01-01'!$F$3:$F$53,C11) -> 7 | E11: =COUNTIF('Qualifier_Analysis_2025-01-01'!$F$3:$F$306,C11) -> 17
C12: Meta | D12: =COUNTIF('Qualifier_Analysis_2025-01-01'!$F$3:$F$53,C12) -> 0 | E12: =COUNTIF('Qualifier_Analysis_2025-01-01'!$F$3:$F$306,C12) -> 18
C13: Sequence | D13: =COUNTIF('Qualifier_Analysis_2025-01-01'!$F$3:$F$53,C13) -> 3 | E13: =COUNTIF('Qualifier_Analysis_2025-01-01'!$F$3:$F$306,C13) -> 7
C14: Provenance | D14: =COUNTIF('Qualifier_Analysis_2025-01-01'!$F$3:$F$53,C14) -> 5 | E14: =COUNTIF('Qualifier_Analysis_2025-01-01'!$F$3:$F$306,C14) -> 12
C15: Causality | D15: =COUNTIF('Qualifier_Analysis_2025-01-01'!$F$3:$F$53,C15) -> 1 | E15: =COUNTIF('Qualifier_Analysis_2025-01-01'!$F$3:$F$306,C15) -> 4
C16: Object/Subject Statement Relation | D16: =COUNTIF('Qualifier_Analysis_2025-01-01'!$F$3:$F$53,C16) -> 2 | E16: =COUNTIF('Qualifier_Analysis_2025-01-01'!$F$3:$F$306,C16) -> 5
C17: Sub-Property or Value | D17: =COUNTIF('Qualifier_Analysis_2025-01-01'!$F$3:$F$53,C17) -> 4 | E17: =COUNTIF('Qualifier_Analysis_2025-01-01'!$F$3:$F$306,C17) -> 9
... C19: Other Additional | D19: =COUNTIF('Qualifier_Analysis_2025-01-01'!$F$3:$F$53,C19) -> 8 | E19: =COUNTIF('Qualifier_Analysis_2025-01-01'!$F$3:$F$306,C19) -> 155
D20: =SUM(D6:D19) -> 50 | E20: =SUM(E6:E19) -> 300
